helpdesk/__init__.py
helpdesk/admin.py
helpdesk/akismet.py
helpdesk/apps.py
helpdesk/decorators.py
helpdesk/forms.py
helpdesk/lib.py
helpdesk/models.py
helpdesk/settings.py
helpdesk/urls.py
helpdesk/.idea/misc.xml
helpdesk/.idea/modules.xml
helpdesk/.idea/workspace.xml
helpdesk/.idea/inspectionProfiles/Project_Default.xml
helpdesk/.idea/inspectionProfiles/profiles_settings.xml
helpdesk/fixtures/emailtemplate.json
helpdesk/locale/ar/LC_MESSAGES/django.mo
helpdesk/locale/ar/LC_MESSAGES/django.po
helpdesk/locale/ca/LC_MESSAGES/django.mo
helpdesk/locale/ca/LC_MESSAGES/django.po
helpdesk/locale/cs/LC_MESSAGES/django.mo
helpdesk/locale/cs/LC_MESSAGES/django.po
helpdesk/locale/de/LC_MESSAGES/django.mo
helpdesk/locale/de/LC_MESSAGES/django.po
helpdesk/locale/el/LC_MESSAGES/django.mo
helpdesk/locale/el/LC_MESSAGES/django.po
helpdesk/locale/en/LC_MESSAGES/django.mo
helpdesk/locale/en/LC_MESSAGES/django.po
helpdesk/locale/es/LC_MESSAGES/django.mo
helpdesk/locale/es/LC_MESSAGES/django.po
helpdesk/locale/es_CO/LC_MESSAGES/django.mo
helpdesk/locale/es_CO/LC_MESSAGES/django.po
helpdesk/locale/es_MX/LC_MESSAGES/django.mo
helpdesk/locale/es_MX/LC_MESSAGES/django.po
helpdesk/locale/fa_IR/LC_MESSAGES/django.mo
helpdesk/locale/fa_IR/LC_MESSAGES/django.po
helpdesk/locale/fi/LC_MESSAGES/django.mo
helpdesk/locale/fi/LC_MESSAGES/django.po
helpdesk/locale/fr/LC_MESSAGES/django.mo
helpdesk/locale/fr/LC_MESSAGES/django.po
helpdesk/locale/he_IL/LC_MESSAGES/django.mo
helpdesk/locale/he_IL/LC_MESSAGES/django.po
helpdesk/locale/hr/LC_MESSAGES/django.mo
helpdesk/locale/hr/LC_MESSAGES/django.po
helpdesk/locale/hu/LC_MESSAGES/django.mo
helpdesk/locale/hu/LC_MESSAGES/django.po
helpdesk/locale/it/LC_MESSAGES/django.mo
helpdesk/locale/it/LC_MESSAGES/django.po
helpdesk/locale/lv/LC_MESSAGES/django.mo
helpdesk/locale/lv/LC_MESSAGES/django.po
helpdesk/locale/nb_NO/LC_MESSAGES/django.mo
helpdesk/locale/nb_NO/LC_MESSAGES/django.po
helpdesk/locale/pl/LC_MESSAGES/django.mo
helpdesk_achange-2.0.dist-info/LICENSE
helpdesk_achange-2.0.dist-info/METADATA
helpdesk_achange-2.0.dist-info/WHEEL
helpdesk_achange-2.0.dist-info/top_level.txt
helpdesk_achange-2.0.dist-info/RECORD
