Metadata-Version: 2.1
Name: helpdesk-achange
Version: 2.0
Summary: ticketing project
Home-page: https://github.com/pypa/django3-helpdesk
Author: alireza
Author-email: alirezaghaempanah2015@gmail.com
License: UNKNOWN
Platform: UNKNOWN
Classifier: Programming Language :: Python :: 3
Classifier: License :: OSI Approved :: MIT License
Classifier: Operating System :: OS Independent
Requires-Python: >=3.6
